google_ngrams/__init__.py
google_ngrams/ngrams.py
google_ngrams/scatter_helpers.py
google_ngrams/vnc.py
google_ngrams/vnc_helpers.py
google_ngrams/data/__init__.py
google_ngrams/data/googlebooks_eng_all_totalcounts_20120701.parquet
google_ngrams/data/googlebooks_eng_gb_all_totalcounts_20120701.parquet
google_ngrams/data/googlebooks_eng_us_all_totalcounts_20120701.parquet
google_ngrams-0.2.0.dist-info/licenses/LICENSE
google_ngrams-0.2.0.dist-info/METADATA
google_ngrams-0.2.0.dist-info/WHEEL
google_ngrams-0.2.0.dist-info/top_level.txt
google_ngrams-0.2.0.dist-info/RECORD
