Metadata-Version: 2.4
Name: google_ngrams
Version: 0.2.0
Summary: Fetch and analyze Google Ngram data for specified word forms.
Author-email: David Brown <dwb2@andrew.cmu.edu>
Maintainer-email: David Brown <dwb2@andrew.cmu.edu>
License-Expression: MIT
Project-URL: Documentation, https://browndw.github.io/google_ngrams
Project-URL: Homepage, https://github.com/browndw/google_ngrams
Keywords: nlp,language
Classifier: Programming Language :: Python :: 3 :: Only
Classifier: Programming Language :: Python :: 3.10
Classifier: Programming Language :: Python :: 3.11
Classifier: Programming Language :: Python :: 3.12
Classifier: Intended Audience :: Science/Research
Classifier: Topic :: Text Processing :: Linguistic
Classifier: Operating System :: OS Independent
Requires-Python: >=3.10
License-File: LICENSE
Requires-Dist: numpy>=1.22
Requires-Dist: matplotlib>=3.5
Requires-Dist: polars>=1.17
Provides-Extra: test
Requires-Dist: pytest>=7.0; extra == "test"
Requires-Dist: pytest-cov>=4.0; extra == "test"
Provides-Extra: dev
Requires-Dist: pytest>=7.0; extra == "dev"
Requires-Dist: pytest-cov>=4.0; extra == "dev"
Requires-Dist: build>=1.0.0; extra == "dev"
Requires-Dist: twine>=5.0.0; extra == "dev"
Dynamic: license-file
